<ColorTriangle><Q_Triangle_A><Point_A><x>0.91777784</x><y>0.97142863</y><r>0.5</r><g>1</g><b>0.3</b></Point_A><Point_B><x>0.8177779</x><y>0.8714286</y><r>1</r><g>0</g><b>0</b></Point_B><Point_C><x>1.0177778</x><y>0.8714286</y><r>0</r><g>1</g><b>0</b></Point_C><is_object>false</is_object></Q_Triangle_A><Q_Triangle_B><Point_A><x>0.8177779</x><y>0.6714286</y><r>0</r><g>0</g><b>1</b></Point_A><Point_B><x>0.8177779</x><y>0.8714286</y><r>1</r><g>0</g><b>0</b></Point_B><Point_C><x>1.0177778</x><y>0.8714286</y><r>0</r><g>1</g><b>0</b></Point_C><is_object>false</is_object></Q_Triangle_B><is_object>true</is_object></ColorTriangle>